together_node/__init__.py
together_node/src/__init__.py
together_node/src/constants.py
together_node/src/model.py
together_node/src/script_composer.py
together_node/src/system.py
together_node/src/utility.py
together_node/src/backend/__init__.py
together_node/src/backend/docker.py
together_node/src/backend/singularity.py
together_node/src/clusters/__init__.py
together_node/src/clusters/baremetal.py
together_node/src/clusters/slurm.py
together_node/src/core/__init__.py
together_node/src/core/render.py
together_node-0.0.37.data/scripts/together_node
together_node-0.0.37.dist-info/METADATA
together_node-0.0.37.dist-info/WHEEL
together_node-0.0.37.dist-info/top_level.txt
together_node-0.0.37.dist-info/RECORD
