Metadata-Version: 2.1
Name: together-node
Version: 0.0.37
Summary: Together Node is a tool to help you join together computer
Author: Xiaozhe Yao
Author-email: askxzyao@gmail.com
Requires-Dist: typer
Requires-Dist: requests
Requires-Dist: rich
Requires-Dist: loguru
